{
  "version": 2,
  "status": "quiet-ground-production-pilot",
  "layoutRevision": 12,
  "cellSize": 32,
  "minimumBlockedCellCoverage": 0.55,
  "map": {
    "id": "camp_randall",
    "ground": {
      "texture": "camp-prod-camp-randall-ground",
      "path": "./assets/camp-production/camp_randall_ground_v2.png"
    },
    "base": {
      "texture": "camp-prod-camp-randall-base",
      "path": "./assets/camp-production/camp_randall_base_v2.png"
    },
    "objects": [
      {
        "id": "memory_garden_west",
        "texture": "camp-prod-camp-randall-memory_garden_west",
        "path": "./assets/camp-production/camp-randall__memory_garden_west.png",
        "x": 14,
        "y": 10,
        "width": 6,
        "height": 4,
        "depth": 447,
        "audit": {
          "blockedCellCount": 16,
          "minimumCoverage": 0.8115,
          "coverage": {
            "0,0": 0.9619,
            "1,0": 0.9678,
            "2,0": 0.8223,
            "3,0": 0.8115,
            "4,0": 0.96,
            "5,0": 0.9473,
            "0,1": 0.9512,
            "5,1": 0.9521,
            "0,2": 0.9512,
            "5,2": 0.9541,
            "0,3": 0.9814,
            "1,3": 0.998,
            "2,3": 0.8682,
            "3,3": 0.873,
            "4,3": 0.999,
            "5,3": 0.9883
          }
        },
        "ownerGroup": "blockers"
      },
      {
        "id": "memory_garden_east",
        "texture": "camp-prod-camp-randall-memory_garden_east",
        "path": "./assets/camp-production/camp-randall__memory_garden_east.png",
        "x": 28,
        "y": 10,
        "width": 6,
        "height": 4,
        "depth": 447,
        "audit": {
          "blockedCellCount": 16,
          "minimumCoverage": 0.8115,
          "coverage": {
            "0,0": 0.9619,
            "1,0": 0.9678,
            "2,0": 0.8223,
            "3,0": 0.8115,
            "4,0": 0.96,
            "5,0": 0.9473,
            "0,1": 0.9512,
            "5,1": 0.9521,
            "0,2": 0.9512,
            "5,2": 0.9541,
            "0,3": 0.9814,
            "1,3": 0.998,
            "2,3": 0.8682,
            "3,3": 0.873,
            "4,3": 0.999,
            "5,3": 0.9883
          }
        },
        "ownerGroup": "blockers"
      },
      {
        "id": "team_building",
        "texture": "camp-prod-camp-randall-team_building",
        "path": "./assets/camp-production/camp-randall__team_building.png",
        "x": 5,
        "y": 14,
        "width": 7,
        "height": 4,
        "depth": 575,
        "audit": {
          "blockedCellCount": 27,
          "minimumCoverage": 0.7178,
          "coverage": {
            "0,0": 0.8018,
            "1,0": 1.0,
            "2,0": 1.0,
            "3,0": 1.0,
            "4,0": 1.0,
            "5,0": 1.0,
            "6,0": 0.8086,
            "0,1": 0.9375,
            "1,1": 1.0,
            "2,1": 1.0,
            "3,1": 1.0,
            "4,1": 1.0,
            "5,1": 1.0,
            "6,1": 0.9375,
            "0,2": 0.9375,
            "1,2": 1.0,
            "2,2": 1.0,
            "3,2": 1.0,
            "4,2": 1.0,
            "5,2": 1.0,
            "6,2": 0.9375,
            "0,3": 0.9961,
            "1,3": 1.0,
            "2,3": 0.7178,
            "4,3": 0.7246,
            "5,3": 1.0,
            "6,3": 0.9971
          }
        },
        "ownerGroup": "buildings"
      },
      {
        "id": "coach_office",
        "texture": "camp-prod-camp-randall-coach_office",
        "path": "./assets/camp-production/camp-randall__coach_office.png",
        "x": 36,
        "y": 14,
        "width": 6,
        "height": 4,
        "depth": 575,
        "audit": {
          "blockedCellCount": 23,
          "minimumCoverage": 0.7324,
          "coverage": {
            "0,0": 0.9219,
            "1,0": 1.0,
            "2,0": 1.0,
            "3,0": 1.0,
            "4,0": 1.0,
            "5,0": 0.9209,
            "0,1": 1.0,
            "1,1": 1.0,
            "2,1": 1.0,
            "3,1": 1.0,
            "4,1": 1.0,
            "5,1": 1.0,
            "0,2": 0.957,
            "1,2": 1.0,
            "2,2": 1.0,
            "3,2": 1.0,
            "4,2": 1.0,
            "5,2": 0.9551,
            "0,3": 0.998,
            "1,3": 0.957,
            "3,3": 0.7324,
            "4,3": 0.9717,
            "5,3": 0.9453
          }
        },
        "ownerGroup": "buildings"
      },
      {
        "id": "camp_randall_stadium",
        "texture": "camp-prod-camp-randall-camp_randall_stadium",
        "path": "./assets/camp-production/camp-randall__camp_randall_stadium.png",
        "x": 16,
        "y": 1,
        "width": 15,
        "height": 6,
        "depth": 223,
        "audit": {
          "blockedCellCount": 89,
          "minimumCoverage": 1.0,
          "coverage": {
            "0,0": 1.0,
            "1,0": 1.0,
            "2,0": 1.0,
            "3,0": 1.0,
            "4,0": 1.0,
            "5,0": 1.0,
            "6,0": 1.0,
            "7,0": 1.0,
            "8,0": 1.0,
            "9,0": 1.0,
            "10,0": 1.0,
            "11,0": 1.0,
            "12,0": 1.0,
            "13,0": 1.0,
            "14,0": 1.0,
            "0,1": 1.0,
            "1,1": 1.0,
            "2,1": 1.0,
            "3,1": 1.0,
            "4,1": 1.0,
            "5,1": 1.0,
            "6,1": 1.0,
            "7,1": 1.0,
            "8,1": 1.0,
            "9,1": 1.0,
            "10,1": 1.0,
            "11,1": 1.0,
            "12,1": 1.0,
            "13,1": 1.0,
            "14,1": 1.0,
            "0,2": 1.0,
            "1,2": 1.0,
            "2,2": 1.0,
            "3,2": 1.0,
            "4,2": 1.0,
            "5,2": 1.0,
            "6,2": 1.0,
            "7,2": 1.0,
            "8,2": 1.0,
            "9,2": 1.0,
            "10,2": 1.0,
            "11,2": 1.0,
            "12,2": 1.0,
            "13,2": 1.0,
            "14,2": 1.0,
            "0,3": 1.0,
            "1,3": 1.0,
            "2,3": 1.0,
            "3,3": 1.0,
            "4,3": 1.0,
            "5,3": 1.0,
            "6,3": 1.0,
            "7,3": 1.0,
            "8,3": 1.0,
            "9,3": 1.0,
            "10,3": 1.0,
            "11,3": 1.0,
            "12,3": 1.0,
            "13,3": 1.0,
            "14,3": 1.0,
            "0,4": 1.0,
            "1,4": 1.0,
            "2,4": 1.0,
            "3,4": 1.0,
            "4,4": 1.0,
            "5,4": 1.0,
            "6,4": 1.0,
            "7,4": 1.0,
            "8,4": 1.0,
            "9,4": 1.0,
            "10,4": 1.0,
            "11,4": 1.0,
            "12,4": 1.0,
            "13,4": 1.0,
            "14,4": 1.0,
            "0,5": 1.0,
            "1,5": 1.0,
            "2,5": 1.0,
            "3,5": 1.0,
            "4,5": 1.0,
            "5,5": 1.0,
            "6,5": 1.0,
            "8,5": 1.0,
            "9,5": 1.0,
            "10,5": 1.0,
            "11,5": 1.0,
            "12,5": 1.0,
            "13,5": 1.0,
            "14,5": 1.0
          }
        },
        "ownerGroup": "landmarks"
      }
    ],
    "actors": [
      {
        "id": "assistant_coach",
        "sheet": "coach",
        "x": 26,
        "y": 20,
        "facing": "left",
        "solid": true,
        "dialogue": "Camp Randall is home. The Team Building is west across the quad."
      }
    ]
  },
  "interiors": {
    "team_locker_room": {
      "base": {
        "texture": "camp-prod-team_locker_room-base",
        "path": "./assets/camp-production/team_locker_room_base_v2.png"
      },
      "objects": [
        {
          "id": "wrestling_door",
          "texture": "camp-prod-team-locker-room-wrestling_door",
          "path": "./assets/camp-production/team-locker-room__wrestling_door.png",
          "x": 7,
          "y": 0,
          "width": 1,
          "height": 1,
          "depth": 31,
          "audit": {
            "blockedCellCount": 0,
            "minimumCoverage": 1,
            "coverage": {}
          }
        },
        {
          "id": "player_lockers",
          "texture": "camp-prod-team-locker-room-player_lockers",
          "path": "./assets/camp-production/team-locker-room__player_lockers.png",
          "x": 1,
          "y": 1,
          "width": 4,
          "height": 2,
          "depth": 95,
          "audit": {
            "blockedCellCount": 8,
            "minimumCoverage": 0.999,
            "coverage": {
              "0,0": 0.999,
              "1,0": 1.0,
              "2,0": 1.0,
              "3,0": 1.0,
              "0,1": 1.0,
              "1,1": 1.0,
              "2,1": 1.0,
              "3,1": 1.0
            }
          }
        },
        {
          "id": "trophy_case_west",
          "texture": "camp-prod-team-locker-room-trophy_case_west",
          "path": "./assets/camp-production/team-locker-room__trophy_case_west.png",
          "x": 5,
          "y": 1,
          "width": 2,
          "height": 2,
          "depth": 95,
          "audit": {
            "blockedCellCount": 4,
            "minimumCoverage": 0.9375,
            "coverage": {
              "0,0": 0.9375,
              "1,0": 0.9375,
              "0,1": 0.957,
              "1,1": 0.957
            }
          }
        },
        {
          "id": "trophy_case_east",
          "texture": "camp-prod-team-locker-room-trophy_case_east",
          "path": "./assets/camp-production/team-locker-room__trophy_case_east.png",
          "x": 8,
          "y": 1,
          "width": 2,
          "height": 2,
          "depth": 95,
          "audit": {
            "blockedCellCount": 4,
            "minimumCoverage": 0.8838,
            "coverage": {
              "0,0": 0.8838,
              "1,0": 0.9141,
              "0,1": 0.9131,
              "1,1": 0.9355
            }
          }
        },
        {
          "id": "rex_lockers",
          "texture": "camp-prod-team-locker-room-rex_lockers",
          "path": "./assets/camp-production/team-locker-room__rex_lockers.png",
          "x": 10,
          "y": 1,
          "width": 4,
          "height": 2,
          "depth": 95,
          "audit": {
            "blockedCellCount": 8,
            "minimumCoverage": 1.0,
            "coverage": {
              "0,0": 1.0,
              "1,0": 1.0,
              "2,0": 1.0,
              "3,0": 1.0,
              "0,1": 1.0,
              "1,1": 1.0,
              "2,1": 1.0,
              "3,1": 1.0
            }
          }
        },
        {
          "id": "bench_west",
          "texture": "camp-prod-team-locker-room-bench_west",
          "path": "./assets/camp-production/team-locker-room__bench_west.png",
          "x": 2,
          "y": 6,
          "width": 3,
          "height": 1,
          "depth": 223,
          "audit": {
            "blockedCellCount": 3,
            "minimumCoverage": 0.7451,
            "coverage": {
              "0,0": 0.751,
              "1,0": 0.7451,
              "2,0": 0.752
            }
          }
        },
        {
          "id": "bench_east",
          "texture": "camp-prod-team-locker-room-bench_east",
          "path": "./assets/camp-production/team-locker-room__bench_east.png",
          "x": 10,
          "y": 6,
          "width": 3,
          "height": 1,
          "depth": 223,
          "audit": {
            "blockedCellCount": 3,
            "minimumCoverage": 0.7451,
            "coverage": {
              "0,0": 0.752,
              "1,0": 0.7451,
              "2,0": 0.751
            }
          }
        },
        {
          "id": "locker_exit_frame",
          "texture": "camp-prod-team-locker-room-locker_exit_frame",
          "path": "./assets/camp-production/team-locker-room__locker_exit_frame.png",
          "x": 6,
          "y": 8,
          "width": 3,
          "height": 1,
          "depth": 287,
          "audit": {
            "blockedCellCount": 0,
            "minimumCoverage": 1,
            "coverage": {}
          }
        }
      ],
      "actors": [
        {
          "id": "captain",
          "sheet": "captain",
          "x": 7,
          "y": 4,
          "facing": "down",
          "solid": true,
          "condition": "office_unchecked",
          "dialogue": "Captain: Coach is not in here. Check his office next door first."
        },
        {
          "id": "rex_locker",
          "sheet": "rex",
          "x": 11,
          "y": 4,
          "facing": "left",
          "solid": true,
          "dialogue": "Rex: Same room. Same weight. We settle the spot on the mat."
        }
      ]
    },
    "wrestling_room": {
      "base": {
        "texture": "camp-prod-wrestling_room-base",
        "path": "./assets/camp-production/wrestling_room_base_v2.png"
      },
      "objects": [
        {
          "id": "weights",
          "texture": "camp-prod-wrestling-room-weights",
          "path": "./assets/camp-production/wrestling-room__weights.png",
          "x": 1,
          "y": 2,
          "width": 2,
          "height": 3,
          "depth": 159,
          "audit": {
            "blockedCellCount": 6,
            "minimumCoverage": 0.665,
            "coverage": {
              "0,0": 0.8359,
              "1,0": 0.665,
              "0,1": 0.8643,
              "1,1": 0.8975,
              "0,2": 0.8203,
              "1,2": 0.8066
            }
          }
        },
        {
          "id": "practice_station",
          "texture": "camp-prod-wrestling-room-practice_station",
          "path": "./assets/camp-production/wrestling-room__practice_station.png",
          "x": 12,
          "y": 2,
          "width": 2,
          "height": 3,
          "depth": 159,
          "audit": {
            "blockedCellCount": 6,
            "minimumCoverage": 0.8809,
            "coverage": {
              "0,0": 0.8867,
              "1,0": 0.8877,
              "0,1": 0.9375,
              "1,1": 0.9375,
              "0,2": 0.8818,
              "1,2": 0.8809
            }
          }
        },
        {
          "id": "wrestling_exit_frame",
          "texture": "camp-prod-wrestling-room-wrestling_exit_frame",
          "path": "./assets/camp-production/wrestling-room__wrestling_exit_frame.png",
          "x": 6,
          "y": 8,
          "width": 3,
          "height": 1,
          "depth": 287,
          "audit": {
            "blockedCellCount": 0,
            "minimumCoverage": 1,
            "coverage": {}
          }
        }
      ],
      "actors": [
        {
          "id": "coach",
          "sheet": "coach",
          "x": 7,
          "y": 5,
          "facing": "down",
          "solid": true,
          "dialogue": "Coach: Your persona is how you impose yourself on a match."
        },
        {
          "id": "rex_mat",
          "sheet": "rex",
          "x": 9,
          "y": 5,
          "facing": "left",
          "solid": true,
          "dialogue": "Rex: Pick your style. Then wrestle me for the spot."
        }
      ]
    },
    "coach_office": {
      "base": {
        "texture": "camp-prod-coach_office-base",
        "path": "./assets/camp-production/coach_office_base_v2.png"
      },
      "objects": [
        {
          "id": "coach_desk",
          "texture": "camp-prod-coach-office-coach_desk",
          "path": "./assets/camp-production/coach-office__coach_desk.png",
          "x": 3,
          "y": 2,
          "width": 5,
          "height": 3,
          "depth": 159,
          "audit": {
            "blockedCellCount": 11,
            "minimumCoverage": 0.9375,
            "coverage": {
              "2,0": 0.9941,
              "0,1": 0.9678,
              "1,1": 0.9785,
              "2,1": 1.0,
              "3,1": 0.9775,
              "4,1": 0.9668,
              "0,2": 0.9424,
              "1,2": 0.958,
              "2,2": 0.9375,
              "3,2": 0.9678,
              "4,2": 0.9531
            }
          }
        },
        {
          "id": "recruit_board",
          "texture": "camp-prod-coach-office-recruit_board",
          "path": "./assets/camp-production/coach-office__recruit_board.png",
          "x": 1,
          "y": 1,
          "width": 3,
          "height": 1,
          "depth": 63,
          "audit": {
            "blockedCellCount": 3,
            "minimumCoverage": 0.9727,
            "coverage": {
              "0,0": 0.9727,
              "1,0": 1.0,
              "2,0": 0.9727
            }
          }
        },
        {
          "id": "depth_chart",
          "texture": "camp-prod-coach-office-depth_chart",
          "path": "./assets/camp-production/coach-office__depth_chart.png",
          "x": 8,
          "y": 1,
          "width": 2,
          "height": 2,
          "depth": 95,
          "audit": {
            "blockedCellCount": 4,
            "minimumCoverage": 0.9814,
            "coverage": {
              "0,0": 0.9854,
              "1,0": 1.0,
              "0,1": 0.9814,
              "1,1": 1.0
            }
          }
        },
        {
          "id": "office_plant",
          "texture": "camp-prod-coach-office-office_plant",
          "path": "./assets/camp-production/coach-office__office_plant.png",
          "x": 1,
          "y": 4,
          "width": 1,
          "height": 2,
          "depth": 191,
          "audit": {
            "blockedCellCount": 2,
            "minimumCoverage": 0.665,
            "coverage": {
              "0,0": 0.7568,
              "0,1": 0.665
            }
          }
        },
        {
          "id": "office_exit_frame",
          "texture": "camp-prod-coach-office-office_exit_frame",
          "path": "./assets/camp-production/coach-office__office_exit_frame.png",
          "x": 4,
          "y": 6,
          "width": 3,
          "height": 1,
          "depth": 223,
          "audit": {
            "blockedCellCount": 0,
            "minimumCoverage": 1,
            "coverage": {}
          }
        }
      ],
      "actors": []
    },
    "stadium_tunnel": {
      "base": {
        "texture": "camp-prod-stadium_tunnel-base",
        "path": "./assets/camp-production/stadium_tunnel_base_v2.png"
      },
      "objects": [],
      "actors": []
    }
  },
  "actorSheets": {
    "player": {
      "texture": "camp-prod-actor-player",
      "path": "./assets/camp-production/actor_player.png",
      "frameWidth": 32,
      "frameHeight": 64,
      "directions": {
        "down": 0,
        "left": 1,
        "right": 2,
        "up": 3
      }
    },
    "captain": {
      "texture": "camp-prod-actor-captain",
      "path": "./assets/camp-production/actor_captain.png",
      "frameWidth": 32,
      "frameHeight": 64,
      "directions": {
        "down": 0,
        "left": 1,
        "right": 2,
        "up": 3
      }
    },
    "coach": {
      "texture": "camp-prod-actor-coach",
      "path": "./assets/camp-production/actor_coach.png",
      "frameWidth": 32,
      "frameHeight": 64,
      "directions": {
        "down": 0,
        "left": 1,
        "right": 2,
        "up": 3
      }
    },
    "rex": {
      "texture": "camp-prod-actor-rex",
      "path": "./assets/camp-production/actor_rex.png",
      "frameWidth": 32,
      "frameHeight": 64,
      "directions": {
        "down": 0,
        "left": 1,
        "right": 2,
        "up": 3
      }
    },
    "trainer": {
      "texture": "camp-prod-actor-trainer",
      "path": "./assets/camp-production/actor_trainer.png",
      "frameWidth": 32,
      "frameHeight": 64,
      "directions": {
        "down": 0,
        "left": 1,
        "right": 2,
        "up": 3
      }
    },
    "wrestler": {
      "texture": "camp-prod-actor-wrestler",
      "path": "./assets/camp-production/actor_wrestler.png",
      "frameWidth": 32,
      "frameHeight": 64,
      "directions": {
        "down": 0,
        "left": 1,
        "right": 2,
        "up": 3
      }
    },
    "manager": {
      "texture": "camp-prod-actor-manager",
      "path": "./assets/camp-production/actor_manager.png",
      "frameWidth": 32,
      "frameHeight": 64,
      "directions": {
        "down": 0,
        "left": 1,
        "right": 2,
        "up": 3
      }
    },
    "scout": {
      "texture": "camp-prod-actor-scout",
      "path": "./assets/camp-production/actor_scout.png",
      "frameWidth": 32,
      "frameHeight": 64,
      "directions": {
        "down": 0,
        "left": 1,
        "right": 2,
        "up": 3
      }
    },
    "student": {
      "texture": "camp-prod-actor-student",
      "path": "./assets/camp-production/actor_student.png",
      "frameWidth": 32,
      "frameHeight": 64,
      "directions": {
        "down": 0,
        "left": 1,
        "right": 2,
        "up": 3
      }
    },
    "official": {
      "texture": "camp-prod-actor-official",
      "path": "./assets/camp-production/actor_official.png",
      "frameWidth": 32,
      "frameHeight": 64,
      "directions": {
        "down": 0,
        "left": 1,
        "right": 2,
        "up": 3
      }
    },
    "athlete": {
      "texture": "camp-prod-actor-athlete",
      "path": "./assets/camp-production/actor_athlete.png",
      "frameWidth": 32,
      "frameHeight": 64,
      "directions": {
        "down": 0,
        "left": 1,
        "right": 2,
        "up": 3
      }
    },
    "camper": {
      "texture": "camp-prod-actor-camper",
      "path": "./assets/camp-production/actor_camper.png",
      "frameWidth": 32,
      "frameHeight": 64,
      "directions": {
        "down": 0,
        "left": 1,
        "right": 2,
        "up": 3
      }
    }
  },
  "sources": {
    "manifest": "77c3aaafc85a9a89d4ff1ecef9eb1fa0e6c21be76eb1fd628c9db0a9baee6ba6",
    "layout": "bde88bac36545558cb9a5550f4358971050c28cdf6ff532c637d02080b3c7cb0",
    "worldTileset": "fa97850371b47e41b1d50222a0ced6fa78d66d1e39ea98acb99664887a4e526e",
    "terrain": "6ed76ba705f5b1b4cf200fbc918279db75a151c21812a3a02edc6a02cc27d9e6",
    "exterior": "25f24c0f9d6d35e05c2439b105b4f7cf72e6200dcc37003998535aac8d9e75ef",
    "locker": "3c3ed974a3979f841eba61722f637d8cc393c077291b82654abcb6af90d6cd64",
    "office": "8b5087925fe7e57c231463e64261b5f39bace9f33a7b83a2b57cb0a346851dea",
    "player": "5b31125c86b08730c61ad49fec5eba2b1bdc03f52c8bee957da287c9eb23e97f",
    "captain": "508f13aacece318231e06870ba1545caa40b438d672ea17bf266eb3a37f02948",
    "coach": "33f444c401c30d11e23372887b54ad13db521481c95a1b956fdd6cb39ee389a7",
    "rex": "9294959ba16668f56957f60c93740cfc359cf61f0559cbd2fe4ddec3b67267db",
    "trainer": "ac8d2150aaf5eede6cd7467f402c3c0b11eb2a4baf0920c7fc78b8eb0d6dd950",
    "wrestler": "06ceb110f72ca8b295431b06733554774c1c7fbec7ab5e2f77f72c288d5b07b5",
    "manager": "45fe4ff5fc3dde20cefe5df3b40d2ed1e86d364a4bb536b09c1ba64248f6b634",
    "scout": "a56e648229724b44eaead49833ea88f0d44d1c8a6bff5b4788c9478cf085d037",
    "student": "bd0c8cc4e74255ab7516cee419dceb079152aafb0b979f1e0623073e274f5150",
    "official": "b0a5736424b618128e31147c6a57886254643738db22b5ea07372775d9112697",
    "athlete": "6a66f602cb6376331ecdacf1ad7c65f8fc3fcf655352910c579ed8697bc36f7e",
    "camper": "019c355d0ac6072f15611ecc5c95ef997876ac8cf31994c96cab1a1344772698"
  },
  "outputs": {
    "actor_athlete.png": "af48b78d9337f6235e085959fd83142bdb73908c2d6e8388e9c6efc206a6ab35",
    "actor_camper.png": "30a758d88a0179290bb7ae89061a537d435a9af1fffdd6be1008a21306ff35cf",
    "actor_captain.png": "8c5cc7e0b31d4472f078b1a7412bbe8dfa3cb623a91c4a7285c8763282386702",
    "actor_coach.png": "3b4d122eea8699f577ce5395cf3656ab03f505457a481c3186fc9e391b043771",
    "actor_manager.png": "fffdb31ce44325751505e2ac921b3ba879effe52e7e78cf47eb72ae81da46484",
    "actor_official.png": "c2b1ea0cd162e6eaa8a4a6630054af92431314d7191fd3ac76de35654a5f5817",
    "actor_player.png": "a0a6cd9a8338e4d2aaf8275b09e1991cda2b217212fe806f32308bafb324c02c",
    "actor_rex.png": "ac27505cf2138481b69a28f37536fc2df25e872749bc084ea78640468e0d7cc6",
    "actor_scout.png": "8cd0c4dc1069b79a9b4bb9cf163cbf167b9c98c4222f69f42a7bf8a689df4004",
    "actor_student.png": "fdad4ba0f9f750e2ec97214c1ba144e87ecaf74250dbe8c6f7ec555554ad0876",
    "actor_trainer.png": "b3da3ceefc650b57e8dfa2dd94263eadaa5ccbbf8f71c9615b079a263955bced",
    "actor_wrestler.png": "8abfde29cd5ffdbbf272885de54154592abe3b0b7feb0648e3629f18c1e2e0b5",
    "camp-randall__camp_randall_stadium.png": "ee9c429db38e2cec10a4cd09586ccad396752755172282c80743cc0c7510378e",
    "camp-randall__coach_office.png": "52788f1713f3a5bbc445597804066b061bdd6e54f1b21ad42b0095d22c3f423f",
    "camp-randall__memory_garden_east.png": "b5e9797dbd10f7893b4e475d477fa61cbd6cca5e22778b635bf4ff67b91edd4f",
    "camp-randall__memory_garden_west.png": "b5e9797dbd10f7893b4e475d477fa61cbd6cca5e22778b635bf4ff67b91edd4f",
    "camp-randall__team_building.png": "4732964a1601ac26fda4e9ec285e4d4f788d90f13d32e783eca8ccafa11761a2",
    "camp_randall_base_v2.png": "e2eb99384b19131755e7e33815a2cd3725d0e9d576679c7d03eef7c83c25f1b1",
    "camp_randall_ground_v2.png": "7b19b018abb3071b9e1c4c14cf95296b432baefbd24bbb433d26d3a7d7e2a303",
    "coach-office__coach_desk.png": "b1b8defeb67c4cb051662ce50477d7b2e16379617032904d1aa2d4a5dfeb3e6a",
    "coach-office__depth_chart.png": "0b765670a0215cdee843785d6b008b2164ee0d0805e1bc14c0c045c601b10c73",
    "coach-office__office_exit_frame.png": "35f99d18bf469bd636ffff9b6a30848196c7945647b19500f8bc355f1a044e94",
    "coach-office__office_plant.png": "064b70ad3abc8d353c33ced94a77a9e6f199756f1764c87259b95a2c11e6dfbf",
    "coach-office__recruit_board.png": "146acae348954a45a68a9003ee530e7633b23a34b031373218a4f3c60e8d7a4f",
    "coach_office_base_v2.png": "4781fa9e35de4d034564e2ec7bf933eae0f6fec2155fd531e1b9d3b2209730f3",
    "stadium_tunnel_base_v2.png": "330e6d8db5a2abdab85e063c0c64b54e199a67252cb859a0eb06f7c0d015b1d8",
    "team-locker-room__bench_east.png": "28c810cbfb3e98ede7c6e98d1088636f2442216b3f89821550572b1e5c269080",
    "team-locker-room__bench_west.png": "5c028dbc24fbdea0a46b590e0b569ba25e47ced7bb2a904c9589c4db98ebee4b",
    "team-locker-room__locker_exit_frame.png": "35f99d18bf469bd636ffff9b6a30848196c7945647b19500f8bc355f1a044e94",
    "team-locker-room__player_lockers.png": "c9d8fa1cbe9f28d20bf94746bac6c10dbdbd57174da80d87c362350109a96e47",
    "team-locker-room__rex_lockers.png": "ed3b818c15670b0b0a937bb936513348197f88e3683d3f37b8c7da5577be5f83",
    "team-locker-room__trophy_case_east.png": "bf82a3fb3f22bd58fc8bd89ce18611d7bd3856c2c350d7b93cd48695b7b0d188",
    "team-locker-room__trophy_case_west.png": "beb01eeecaa4e39caa08939fe99f65aa5db2e81000a558dd0de5c442b9f4586b",
    "team-locker-room__wrestling_door.png": "c34615719891e1ec69cbee7cfc25b9430ea027f5442fa2b3ecdc94383eb78e4b",
    "team_locker_room_base_v2.png": "d621a4c81253a4e7789fd2a45e0fad9d52510caf2aaa89bf7a3850581c463ab8",
    "wrestling-room__practice_station.png": "bfc017ffbd6d844ee0f2e24c59e25466f61deadb917022c479274f4972f83d8d",
    "wrestling-room__weights.png": "7ba68638bb1e283ef64490af7f6960d03615411c2af0a07f162a74cb2dada463",
    "wrestling-room__wrestling_exit_frame.png": "35f99d18bf469bd636ffff9b6a30848196c7945647b19500f8bc355f1a044e94",
    "wrestling_room_base_v2.png": "8498cc5d07a99791be42d2dcceaed41561b4e67fbbc6c0d32ec75ab85b4db25a"
  }
}
